dbt_bq_sourcegen/__init__.py
dbt_bq_sourcegen/cli.py
dbt_bq_sourcegen/io/__init__.py
dbt_bq_sourcegen/io/bigquery.py
dbt_bq_sourcegen/io/yaml_handler.py
dbt_bq_sourcegen/logic/__init__.py
dbt_bq_sourcegen/logic/merge_strategy.py
dbt_bq_sourcegen/logic/schema_diff.py
dbt_bq_sourcegen/logic/source_builder.py
dbt_bq_sourcegen/types/__init__.py
dbt_bq_sourcegen/types/bigquery.py
dbt_bq_sourcegen/types/dbt.py
dbt_bq_sourcegen/types/diff.py
dbt_bq_sourcegen-0.1.1.dist-info/METADATA
dbt_bq_sourcegen-0.1.1.dist-info/WHEEL
dbt_bq_sourcegen-0.1.1.dist-info/entry_points.txt
dbt_bq_sourcegen-0.1.1.dist-info/licenses/LICENSE
dbt_bq_sourcegen-0.1.1.dist-info/RECORD
