Metadata-Version: 2.4
Name: dbt-bq-sourcegen
Version: 0.1.1
Summary: Create or update dbt source YAML from BigQuery
Project-URL: Homepage, https://github.com/K-Oxon/dbt-bq-sourcegen
Project-URL: Repository, https://github.com/K-Oxon/dbt-bq-sourcegen
Project-URL: Issues, https://github.com/K-Oxon/dbt-bq-sourcegen/issues
Author-email: K-Oxon <ko1011qfp@gmail.com>
License-File: LICENSE
Keywords: bigquery,dbt,source,yaml
Classifier: Development Status :: 4 - Beta
Classifier: Intended Audience :: Developers
Classifier: License :: OSI Approved :: MIT License
Classifier: Programming Language :: Python :: 3
Classifier: Programming Language :: Python :: 3.11
Classifier: Programming Language :: Python :: 3.12
Classifier: Programming Language :: Python :: 3.13
Classifier: Topic :: Software Development :: Build Tools
Requires-Python: >=3.11
Requires-Dist: click>=8.0
Requires-Dist: google-cloud-bigquery>=3.34.0
Requires-Dist: loguru>=0.7.3
Requires-Dist: pydantic>=2.11.7
Requires-Dist: ruamel-yaml>=0.18.14
